pybartelslabtronix/__init__.py
pybartelslabtronix/bartelslabtronix.py
pybartelslabtronix/classes.py
pybartelslabtronix/py.typed
pybartelslabtronix/version.py
pybartelslabtronix-1.0.1.dist-info/LICENSE
pybartelslabtronix-1.0.1.dist-info/METADATA
pybartelslabtronix-1.0.1.dist-info/WHEEL
pybartelslabtronix-1.0.1.dist-info/top_level.txt
pybartelslabtronix-1.0.1.dist-info/RECORD
